core/__init__.py
core/main.py
starter-project/.gitignore
starter-project/README.md
starter-project/__init__.py
starter-project/dbt_project.yml
starter-project/packages.yml
starter-project/sample.profiles.yml
starter-project/.github/issue_template.md
starter-project/.github/pull_request_template.md
starter-project/analysis/.gitkeep
starter-project/data/.gitkeep
starter-project/macros/.gitkeep
starter-project/macros/get_custom_schema.sql
starter-project/macros/grant_select_on_schemas.sql
starter-project/macros/redshift_maintenance.sql
starter-project/models/admin/warehouse_operation.sql
starter-project/models/marts/.gitkeep
starter-project/models/staging/.gitkeep
starter-project/snapshots/.gitkeep
starter-project/tests/.gitkeep
dbt_init-0.2.7.dist-info/LICENSE
dbt_init-0.2.7.dist-info/METADATA
dbt_init-0.2.7.dist-info/WHEEL
dbt_init-0.2.7.dist-info/entry_points.txt
dbt_init-0.2.7.dist-info/top_level.txt
dbt_init-0.2.7.dist-info/RECORD
